sealionconda/__init__.py
sealionconda/app.py
sealionconda/utils.py
sl_conda-0.0.1.post1.dist-info/METADATA
sl_conda-0.0.1.post1.dist-info/WHEEL
sl_conda-0.0.1.post1.dist-info/entry_points.txt
sl_conda-0.0.1.post1.dist-info/top_level.txt
sl_conda-0.0.1.post1.dist-info/RECORD
