Metadata-Version: 2.1
Name: sl-conda
Version: 0.0.1.post1
Home-page: https://github.com/opensealion/sealion-conda
Author: arkmon
Author-email: 
License: Apache License 2.0
Keywords: sealion-conda,sealionconda,sc
Classifier: Development Status :: 3 - Alpha
Requires-Dist: tqdm
